dropbox_index/__init__.py
dropbox_index/__main__.py
dropbox_index/logic.js
dropbox_index/style.html
dropbox_index/types.txt
icons/application.png
icons/archive.png
icons/asc.png
icons/back.png
icons/code.png
icons/desc.png
icons/document.png
icons/favicon.ico
icons/file.png
icons/folder.png
icons/font.png
icons/icons-info.txt
icons/image.png
icons/iso.png
icons/markup.png
icons/music.png
icons/package.png
icons/pdf.png
icons/plugin.png
icons/presentation.png
icons/spreadhseet.png
icons/spreadsheet.png
icons/txt.png
icons/video.png
dropbox_index-0.6.0.dist-info/LICENSE
dropbox_index-0.6.0.dist-info/METADATA
dropbox_index-0.6.0.dist-info/WHEEL
dropbox_index-0.6.0.dist-info/entry_points.txt
dropbox_index-0.6.0.dist-info/top_level.txt
dropbox_index-0.6.0.dist-info/RECORD
