Metadata-Version: 2.1
Name: dropbox-index
Version: 0.6.0
Summary: Creates index.html for directory contents shared publicly on Dropbox. Easily share whole content of the directory without the need to send separate links for each file.
Home-page: https://github.com/jaraco/dropbox-index
Author: Wojciech 'KosciaK' Pietrzok
Author-email: kosciak@kosciak.net
Maintainer: Jason R. Coombs
Maintainer-email: jaraco@jaraco.com
Classifier: Development Status :: 5 - Production/Stable
Classifier: Intended Audience :: Developers
Classifier: License :: OSI Approved :: MIT License
Classifier: Programming Language :: Python :: 3
Classifier: Programming Language :: Python :: 3 :: Only
Requires-Python: >=3.8
License-File: LICENSE
Requires-Dist: importlib-resources
Provides-Extra: docs
Requires-Dist: sphinx >=3.5 ; extra == 'docs'
Requires-Dist: jaraco.packaging >=9.3 ; extra == 'docs'
Requires-Dist: rst.linker >=1.9 ; extra == 'docs'
Requires-Dist: furo ; extra == 'docs'
Requires-Dist: sphinx-lint ; extra == 'docs'
Provides-Extra: testing
Requires-Dist: pytest >=6 ; extra == 'testing'
Requires-Dist: pytest-checkdocs >=2.4 ; extra == 'testing'
Requires-Dist: pytest-cov ; extra == 'testing'
Requires-Dist: pytest-enabler >=2.2 ; extra == 'testing'
Requires-Dist: pytest-ruff ; extra == 'testing'
Requires-Dist: pytest-black >=0.3.7 ; (platform_python_implementation != "PyPy") and extra == 'testing'
Requires-Dist: pytest-mypy >=0.9.1 ; (platform_python_implementation != "PyPy") and extra == 'testing'
